{"data":[
  {"hour":0,"consumption":1180,"yield":0},
  {"hour":1,"consumption":1150,"yield":0},
  {"hour":2,"consumption":1000,"yield":0},
  {"hour":3,"consumption":1050,"yield":0},
  {"hour":4,"consumption":1000,"yield":0},
  {"hour":5,"consumption":1020,"yield":0},
  {"hour":6,"consumption":1070,"yield":0},
  {"hour":7,"consumption":980,"yield":0},
  {"hour":8,"consumption":1040,"yield":0},
  {"hour":9,"consumption":950,"yield":1000},
  {"hour":10,"consumption":2000,"yield":1050},
  {"hour":11,"consumption":1020,"yield":3000},
  {"hour":12,"consumption":1070,"yield":5000},
  {"hour":13,"consumption":970,"yield":8000},
  {"hour":14,"consumption":1020,"yield":8000},
  {"hour":15,"consumption":1000,"yield":6000},
  {"hour":16,"consumption":990,"yield":3000},
  {"hour":17,"consumption":1000,"yield":300},
  {"hour":18,"consumption":2330,"yield":0},
  {"hour":19,"consumption":3850,"yield":0},
  {"hour":20,"consumption":2140,"yield":0},
  {"hour":21,"consumption":2030,"yield":0},
  {"hour":22,"consumption":1260,"yield":0},
  {"hour":23,"consumption":1110,"yield":0}
  ]
}
